gitlint/__init__.py
gitlint/cache.py
gitlint/cli.py
gitlint/config.py
gitlint/deprecation.py
gitlint/display.py
gitlint/exception.py
gitlint/git.py
gitlint/hooks.py
gitlint/lint.py
gitlint/options.py
gitlint/rule_finder.py
gitlint/rules.py
gitlint/shell.py
gitlint/utils.py
gitlint/contrib/__init__.py
gitlint/contrib/rules/__init__.py
gitlint/contrib/rules/authors_commit.py
gitlint/contrib/rules/conventional_commit.py
gitlint/contrib/rules/disallow_cleanup_commits.py
gitlint/contrib/rules/signedoff_by.py
gitlint/files/commit-msg
gitlint/files/gitlint
gitlint_core-0.19.0.dist-info/METADATA
gitlint_core-0.19.0.dist-info/WHEEL
gitlint_core-0.19.0.dist-info/entry_points.txt
gitlint_core-0.19.0.dist-info/licenses/LICENSE
gitlint_core-0.19.0.dist-info/RECORD
