Metadata-Version: 2.1
Name: gitlint-core
Version: 0.19.0
Summary: Git commit message linter written in python, checks your commit messages for style.
Project-URL: Homepage, https://jorisroovers.github.io/gitlint
Project-URL: Documentation, https://jorisroovers.github.io/gitlint
Project-URL: Source, https://github.com/jorisroovers/gitlint/tree/main/gitlint-core
Project-URL: Changelog, https://github.com/jorisroovers/gitlint/blob/main/CHANGELOG.md
Project-URL: Source Commit, https://github.com/jorisroovers/gitlint/tree/90ff52c9ccddc153d0923bb6e1dd0096311aaa31/gitlint-core
Author: Joris Roovers
License-Expression: MIT
License-File: LICENSE
Keywords: git,gitlint,lint
Classifier: Development Status :: 5 - Production/Stable
Classifier: Environment :: Console
Classifier: Intended Audience :: Developers
Classifier: License :: OSI Approved :: MIT License
Classifier: Operating System :: OS Independent
Classifier: Programming Language :: Python
Classifier: Programming Language :: Python :: 3.7
Classifier: Programming Language :: Python :: 3.8
Classifier: Programming Language :: Python :: 3.9
Classifier: Programming Language :: Python :: 3.10
Classifier: Programming Language :: Python :: 3.11
Classifier: Programming Language :: Python :: Implementation :: CPython
Classifier: Programming Language :: Python :: Implementation :: PyPy
Classifier: Topic :: Software Development :: Quality Assurance
Classifier: Topic :: Software Development :: Testing
Requires-Python: >=3.7
Requires-Dist: arrow>=1
Requires-Dist: click>=8
Requires-Dist: importlib-metadata>=1.0; python_version < '3.8'
Requires-Dist: sh>=1.13.0; sys_platform != 'win32'
Provides-Extra: trusted-deps
Requires-Dist: arrow==1.2.3; extra == 'trusted-deps'
Requires-Dist: click==8.1.3; extra == 'trusted-deps'
Requires-Dist: sh==1.14.3; sys_platform != 'win32' and extra == 'trusted-deps'
